ncg_optimizer/Line_Search.py
ncg_optimizer/__init__.py
ncg_optimizer/basic.py
ncg_optimizer/lcg.py
ncg_optimizer-0.2.2.dist-info/LICENSE
ncg_optimizer-0.2.2.dist-info/METADATA
ncg_optimizer-0.2.2.dist-info/WHEEL
ncg_optimizer-0.2.2.dist-info/top_level.txt
ncg_optimizer-0.2.2.dist-info/RECORD
