Metadata-Version: 2.1
Name: ncg-optimizer
Version: 0.2.2
Summary: PyTorch optimizer based on nonlinear conjugate gradient method
Home-page: https://github.com/RyunMi/NCG-optimizer
Author: Kerun Mi
Author-email: ryunxiaomi@gmail.com
License: Apache 2
Keywords: ncg-optimizer,pytorch,LCG,FR,PRP,HS,CD,DY,LS,HZ,HS-DY,Armijo,Curvature,Strong Wolfe,Weak Wolfe,Goldstein
Classifier: Development Status :: 3 - Alpha
Classifier: Intended Audience :: Developers
Classifier: Intended Audience :: Science/Research
Classifier: Topic :: Scientific/Engineering :: Artificial Intelligence
Classifier: License :: OSI Approved :: Apache Software License
Classifier: Operating System :: POSIX :: Linux
Classifier: Operating System :: MacOS
Classifier: Operating System :: Unix
Classifier: Operating System :: Microsoft :: Windows
Classifier: Operating System :: OS Independent
Classifier: Programming Language :: Python :: 3
Classifier: Programming Language :: Python :: 3.8
Classifier: Programming Language :: Python :: 3.9
Classifier: Programming Language :: Python :: 3.10
Classifier: Programming Language :: Python :: 3.11
License-File: LICENSE
Requires-Dist: torch >=1.7.1
